textual_pandas/__init__.py
textual_pandas/widgets.py
textual_pandas-0.2.3.dist-info/LICENSE
textual_pandas-0.2.3.dist-info/METADATA
textual_pandas-0.2.3.dist-info/WHEEL
textual_pandas-0.2.3.dist-info/RECORD
