Metadata-Version: 2.1
Name: textual-pandas
Version: 0.2.3
Summary: A module to build Textual widgets that represent data from the Pandas library
Home-page: https://github.com/dannywade/textual-pandas
License: MIT
Author: Dan Wade
Author-email: danny.wade35@gmail.com
Requires-Python: >=3.10,<4.0
Classifier: License :: OSI Approved :: MIT License
Classifier: Programming Language :: Python :: 3
Classifier: Programming Language :: Python :: 3.10
Classifier: Programming Language :: Python :: 3.11
Classifier: Programming Language :: Python :: 3.12
Requires-Dist: pandas (<=2.2.3)
Requires-Dist: textual (>=1.0,<4.0)
